tfrecords_pb2.py
tfreecord.py
tfreecord-1.0.0.dist-info/LICENSE
tfreecord-1.0.0.dist-info/METADATA
tfreecord-1.0.0.dist-info/WHEEL
tfreecord-1.0.0.dist-info/top_level.txt
tfreecord-1.0.0.dist-info/RECORD
