Metadata-Version: 2.1
Name: tfreecord
Version: 1.0.0
Summary: UNKNOWN
Home-page: https://github.com/Wikidepia/tfreecord
Author: Wikidepia
License: UNKNOWN
Platform: UNKNOWN
Requires-Dist: crc32c
Requires-Dist: numpy
Requires-Dist: protobuf
